phasefieldx/__init__.py
phasefieldx/errors_functions.py
phasefieldx/files.py
phasefieldx/norms.py
phasefieldx/Boundary/__init__.py
phasefieldx/Boundary/boundary_conditions.py
phasefieldx/Element/__init__.py
phasefieldx/Element/Allen_Cahn/Input.py
phasefieldx/Element/Allen_Cahn/__init__.py
phasefieldx/Element/Allen_Cahn/energy.py
phasefieldx/Element/Allen_Cahn/potential.py
phasefieldx/Element/Allen_Cahn/solver/__init__.py
phasefieldx/Element/Allen_Cahn/solver/solver.py
phasefieldx/Element/Allen_Cahn/solver/solver_static.py
phasefieldx/Element/Elasticity/Input.py
phasefieldx/Element/Elasticity/__init__.py
phasefieldx/Element/Elasticity/energy.py
phasefieldx/Element/Elasticity/solver/__init__.py
phasefieldx/Element/Elasticity/solver/solver.py
phasefieldx/Element/Phase_Field/Input.py
phasefieldx/Element/Phase_Field/__init__.py
phasefieldx/Element/Phase_Field/energy.py
phasefieldx/Element/Phase_Field/geometric_crack.py
phasefieldx/Element/Phase_Field/solver/__init__.py
phasefieldx/Element/Phase_Field/solver/solver.py
phasefieldx/Element/Phase_Field_Fracture/Input.py
phasefieldx/Element/Phase_Field_Fracture/__init__.py
phasefieldx/Element/Phase_Field_Fracture/energy.py
phasefieldx/Element/Phase_Field_Fracture/fatigue_degradation_functions.py
phasefieldx/Element/Phase_Field_Fracture/g_degradation_functions.py
phasefieldx/Element/Phase_Field_Fracture/split_energy_stress_tangent_functions.py
phasefieldx/Element/Phase_Field_Fracture/solver/__init__.py
phasefieldx/Element/Phase_Field_Fracture/solver/solver.py
phasefieldx/Element/Phase_Field_Fracture/solver/solver_anisotropic.py
phasefieldx/Element/Phase_Field_Fracture/solver/solver_ener_non_variational.py
phasefieldx/Element/Phase_Field_Fracture/solver/solver_ener_variational.py
phasefieldx/Loading/__init__.py
phasefieldx/Loading/loading_functions.py
phasefieldx/Logger/__init__.py
phasefieldx/Logger/library_versions.py
phasefieldx/Materials/__init__.py
phasefieldx/Materials/conversion.py
phasefieldx-0.3.0.dist-info/METADATA
phasefieldx-0.3.0.dist-info/WHEEL
phasefieldx-0.3.0.dist-info/licenses/AUTHORS.rst
phasefieldx-0.3.0.dist-info/licenses/LICENSE
phasefieldx-0.3.0.dist-info/RECORD
