Metadata-Version: 2.4
Name: phasefieldx
Version: 0.3.0
Summary: PhaseFieldX: An Open-Source Framework for Advanced Phase-Field Simulations
Project-URL: Homepage, https://github.com/CastillonMiguel/phasefieldx
Project-URL: Documentation, https://phasefieldx.readthedocs.io
Project-URL: Issues, https://github.com/CastillonMiguel/phasefieldx/issues
Author-email: Miguel Castillon <miguel.research@pm.me>
License: MIT License
License-File: AUTHORS.rst
License-File: LICENSE
Keywords: allen cahn,fatigue,finite element,fracture,phase field,phase-field,solidification
Classifier: License :: OSI Approved :: MIT License
Classifier: Operating System :: OS Independent
Classifier: Programming Language :: Python :: 3
Requires-Python: >=3.10
